{
    "7470836911": {
        "balance": 0
    },
    "6127250344": {
        "balance": 0
    },
    "users": {
        "7294623320": {
            "name": "uzbek",
            "balance": 500,
            "last_bonus": 1740298555.2580974
        },
        "7470836911": {
            "name": "Nozimjon",
            "balance": 1000,
            "last_bonus": 1740299013.497631
        },
        "7016524351": {
            "name": "Otabek",
            "balance": 500,
            "last_bonus": 1740300386.0394518
        },
        "8144127879": {
            "name": "\u3164",
            "balance": 500,
            "last_bonus": 1740303521.0856373
        },
        "6127250344": {
            "name": "Abduzohid",
            "balance": 500,
            "last_bonus": 1740308587.462648
        },
        "6522896814": {
            "balance": 808,
            "referred_by": "7470836911",
            "last_bonus": 1740314106.0393088
        }
    },
    "admin": 6127250344
}